query_cpp
query_pts
