Metadata-Version: 2.1
Name: query-pts
Version: 0.2.1
Summary: A package for calculate barycentric coordinates in the tetrahedras.
Home-page: UNKNOWN
Author: SunYangtian
Author-email: sunyangtian98@gmail.com
License: UNKNOWN
Platform: UNKNOWN
License-File: LICENSE
